[{"id":1,"name":"Classic Polo Tee","tag":"evergreen","rating":4.6,"price":301,"raw_price":372,"url":"http://dummyimage.com/400x180.png/dddddd/000000"},
{"id":2,"name":"Retro Striped T-shirt","tag":"evergreen","rating":2.8,"price":558,"raw_price":984,"url":"http://dummyimage.com/400x180.png/dddddd/000000"},
{"id":3,"name":"Basic Solid Tee","tag":"evergreen","rating":2.8,"price":260,"raw_price":836,"url":"http://dummyimage.com/400x180.png/5fa2dd/ffffff"},
{"id":4,"name":"Vintage Washed Shirt","tag":"evergreen","rating":4.9,"price":827,"raw_price":714,"url":"http://dummyimage.com/400x180.png/cc0000/ffffff"},
{"id":5,"name":"Classic Polo Tee","tag":"evergreen","rating":2.4,"price":634,"raw_price":1104,"url":"http://dummyimage.com/400x180.png/dddddd/000000"},
{"id":6,"name":"Graphic Print Tee","tag":"trend","rating":3.3,"price":1057,"raw_price":1067,"url":"http://dummyimage.com/400x180.png/5fa2dd/ffffff"},
{"id":7,"name":"Vintage Washed Shirt","tag":"trend","rating":2.0,"price":652,"raw_price":820,"url":"http://dummyimage.com/400x180.png/dddddd/000000"},
{"id":8,"name":"Slim Fit Henley","tag":"evergreen","rating":3.8,"price":796,"raw_price":352,"url":"http://dummyimage.com/400x180.png/dddddd/000000"},
{"id":9,"name":"Slim Fit Henley","tag":"new","rating":3.0,"price":490,"raw_price":326,"url":"http://dummyimage.com/400x180.png/dddddd/000000"},
{"id":10,"name":"ComfortBlend Crewneck","tag":"new","rating":3.5,"price":1006,"raw_price":639,"url":"http://dummyimage.com/400x180.png/cc0000/ffffff"}]